{
  "id": "a0096bb2-c57e-4c31-b9db-ec111bc682ff",
  "name": "2Earn Partner API - Development",
  "values": [
    {
      "key": "base_url",
      "value": "http://localhost",
      "enabled": true,
      "type": "string"
    },
    {
      "key": "order_id",
      "value": "1",
      "enabled": true,
      "type": "string"
    },
    {
      "key": "item_id",
      "value": "1",
      "enabled": true,
      "type": "string"
    },
    {
      "key": "user_id",
      "value": "1",
      "enabled": true,
      "type": "string"
    },
    {
      "key": "detail_id",
      "value": "1",
      "enabled": true,
      "type": "string"
    }
  ],
  "_postman_variable_scope": "environment"
}